{
    "help": "Execute SQL queries on the DataStore.\n\n    The datastore_search_sql action allows a user to search data in a resource\n    or connect multiple resources with join expressions. The underlying SQL\n    engine is the\n    `PostgreSQL engine <http://www.postgresql.org/docs/9.1/interactive/sql/.html>`_.\n    There is an enforced timeout on SQL queries to avoid an unintended DOS.\n    DataStore resource that belong to a private CKAN resource cannot be searched with\n    this action. Use :meth:`~ckanext.datastore.logic.action.datastore_search` instead.\n\n    .. note:: This action is only available when using PostgreSQL 9.X and using a read-only user on the database.\n        It is not available in :ref:`legacy mode<legacy-mode>`.\n\n    :param sql: a single SQL select statement\n    :type sql: string\n\n    **Results:**\n\n    The result of this action is a dictionary with the following keys:\n\n    :rtype: A dictionary with the following keys\n    :param fields: fields/columns and their extra metadata\n    :type fields: list of dictionaries\n    :param records: list of matching results\n    :type records: list of dictionaries\n\n    ",
    "result": {
        "fields": [
            {
                "id": "_id",
                "type": "int4"
            },
            {
                "id": "_full_text",
                "type": "tsvector"
            },
            {
                "id": "Fecha",
                "type": "text"
            },
            {
                "id": "04/04/2004",
                "type": "text"
            }
        ],
        "records": [
            {
                "04/04/2004": "Elección Municipal",
                "Fecha": "Tipo Elección:",
                "_full_text": "'elección':2,3 'municip':4 'tipo':1",
                "_id": 1
            },
            {
                "04/04/2004": "10",
                "Fecha": "Departamento",
                "_full_text": "'10':2 'departamento':1",
                "_id": 2
            },
            {
                "04/04/2004": "30",
                "Fecha": "Distrito",
                "_full_text": "'30':2 'distrito':1",
                "_id": 3
            },
            {
                "04/04/2004": "986",
                "Fecha": "Habilitados",
                "_full_text": "'986':2 'habilitado':1",
                "_id": 4
            },
            {
                "04/04/2004": "",
                "Fecha": "",
                "_full_text": "",
                "_id": 5
            },
            {
                "04/04/2004": "",
                "Fecha": "Resultados",
                "_full_text": "'resultado':1",
                "_id": 6
            },
            {
                "04/04/2004": "Intendente",
                "Fecha": "Candidatura",
                "_full_text": "'candidatura':1 'intendent':2",
                "_id": 7
            },
            {
                "04/04/2004": "0",
                "Fecha": "MSFQ",
                "_full_text": "'0':2 'msfq':1",
                "_id": 8
            },
            {
                "04/04/2004": "246",
                "Fecha": "UNACE",
                "_full_text": "'246':2 'unac':1",
                "_id": 9
            },
            {
                "04/04/2004": "600",
                "Fecha": "MPIUD",
                "_full_text": "'600':2 'mpiud':1",
                "_id": 10
            },
            {
                "04/04/2004": "14",
                "Fecha": "NULOS",
                "_full_text": "'14':2 'nulo':1",
                "_id": 11
            },
            {
                "04/04/2004": "19",
                "Fecha": "BLANCOS",
                "_full_text": "'19':2 'blanco':1",
                "_id": 12
            },
            {
                "04/04/2004": "879",
                "Fecha": "TOTALES",
                "_full_text": "'879':2 'total':1",
                "_id": 13
            },
            {
                "04/04/2004": "",
                "Fecha": "",
                "_full_text": "",
                "_id": 14
            },
            {
                "04/04/2004": "Electo",
                "Fecha": "LISTA",
                "_full_text": "'electo':2 'lista':1",
                "_id": 15
            },
            {
                "04/04/2004": "ROGELIO MARTINEZ LUGO",
                "Fecha": "MPIUD",
                "_full_text": "'lugo':4 'martinez':3 'mpiud':1 'rogelio':2",
                "_id": 16
            },
            {
                "04/04/2004": "",
                "Fecha": "",
                "_full_text": "",
                "_id": 17
            },
            {
                "04/04/2004": "",
                "Fecha": "",
                "_full_text": "",
                "_id": 18
            },
            {
                "04/04/2004": "Junta Municipal. Integración",
                "Fecha": "Candidatura",
                "_full_text": "'candidatura':1 'integración':4 'junta':2 'municip':3",
                "_id": 19
            },
            {
                "04/04/2004": "Orden",
                "Fecha": "LISTA",
                "_full_text": "'lista':1 'orden':2",
                "_id": 20
            },
            {
                "04/04/2004": "1",
                "Fecha": "MPIUD",
                "_full_text": "'1':2 'mpiud':1",
                "_id": 21
            },
            {
                "04/04/2004": "2",
                "Fecha": "MSFQ",
                "_full_text": "'2':2 'msfq':1",
                "_id": 22
            },
            {
                "04/04/2004": "3",
                "Fecha": "MPIUD",
                "_full_text": "'3':2 'mpiud':1",
                "_id": 23
            },
            {
                "04/04/2004": "4",
                "Fecha": "MSFQ",
                "_full_text": "'4':2 'msfq':1",
                "_id": 24
            },
            {
                "04/04/2004": "5",
                "Fecha": "MPIUD",
                "_full_text": "'5':2 'mpiud':1",
                "_id": 25
            },
            {
                "04/04/2004": "6",
                "Fecha": "UNACE",
                "_full_text": "'6':2 'unac':1",
                "_id": 26
            },
            {
                "04/04/2004": "7",
                "Fecha": "MPIUD",
                "_full_text": "'7':2 'mpiud':1",
                "_id": 27
            },
            {
                "04/04/2004": "8",
                "Fecha": "MSFQ",
                "_full_text": "'8':2 'msfq':1",
                "_id": 28
            },
            {
                "04/04/2004": "9",
                "Fecha": "MPIUD",
                "_full_text": "'9':2 'mpiud':1",
                "_id": 29
            },
            {
                "04/04/2004": "",
                "Fecha": "",
                "_full_text": "",
                "_id": 30
            },
            {
                "04/04/2004": "Orden",
                "Fecha": "LISTA",
                "_full_text": "'lista':1 'orden':2",
                "_id": 31
            },
            {
                "04/04/2004": "1",
                "Fecha": "MPIUD",
                "_full_text": "'1':2 'mpiud':1",
                "_id": 32
            },
            {
                "04/04/2004": "2",
                "Fecha": "MSFQ",
                "_full_text": "'2':2 'msfq':1",
                "_id": 33
            },
            {
                "04/04/2004": "3",
                "Fecha": "MPIUD",
                "_full_text": "'3':2 'mpiud':1",
                "_id": 34
            },
            {
                "04/04/2004": "4",
                "Fecha": "MSFQ",
                "_full_text": "'4':2 'msfq':1",
                "_id": 35
            },
            {
                "04/04/2004": "5",
                "Fecha": "MPIUD",
                "_full_text": "'5':2 'mpiud':1",
                "_id": 36
            },
            {
                "04/04/2004": "6",
                "Fecha": "UNACE",
                "_full_text": "'6':2 'unac':1",
                "_id": 37
            },
            {
                "04/04/2004": "",
                "Fecha": "",
                "_full_text": "",
                "_id": 38
            },
            {
                "04/04/2004": "",
                "Fecha": "",
                "_full_text": "",
                "_id": 39
            },
            {
                "04/04/2004": "",
                "Fecha": "",
                "_full_text": "",
                "_id": 40
            }
        ],
        "sql": "SELECT * FROM \"676769b2-8b50-4b0a-9238-914fc87d7ed8\" ;"
    },
    "success": true
}